{
	"miniprogramRoot": "miniprogram/",
	"cloudfunctionRoot": "cloudfunctions/",
	"setting": {
		"urlCheck": true,
		"es6": true,
		"postcss": true,
		"minified": true,
		"newFeature": true,
		"nodeModules": true
	},
	"appid": "wxd1ca70db507085dd",
	"projectname": "CloudDatabase",
	"libVersion": "2.4.0",
	"condition": {
		"search": {
			"current": -1,
			"list": []
		},
		"conversation": {
			"current": -1,
			"list": []
		},
		"plugin": {
			"current": -1,
			"list": []
		},
		"game": {
			"list": []
		},
		"miniprogram": {
			"current": 5,
			"list": [
				{
					"id": -1,
					"name": "db guide",
					"pathName": "pages/databaseGuide/databaseGuide",
					"query": ""
				},
				{
					"id": -1,
					"name": "add",
					"pathName": "pages/add/add",
					"query": ""
				},
				{
					"id": -1,
					"name": "index",
					"pathName": "pages/index/index",
					"query": ""
				},
				{
					"id": -1,
					"name": "complex",
					"pathName": "pages/complex/complex",
					"query": ""
				},
				{
					"id": 4,
					"name": "info",
					"pathName": "pages/info/info",
					"query": "id=W71Wu92AWotka_oN"
				},
				{
					"id": -1,
					"name": "regex",
					"pathName": "pages/regex/regex"
				}
			]
		}
	}
}